llms.py
lapi-1.0.3.dist-info/licenses/LICENSE
lapi-1.0.3.dist-info/METADATA
lapi-1.0.3.dist-info/WHEEL
lapi-1.0.3.dist-info/entry_points.txt
lapi-1.0.3.dist-info/top_level.txt
lapi-1.0.3.dist-info/RECORD
